gptfy/__init__.py
gptfy/client.py
gptfy/colors.py
gptfy/conversation.py
gptfy/dalle.py
gptfy/model.py
gptfy-0.3.4.dist-info/LICENSE
gptfy-0.3.4.dist-info/METADATA
gptfy-0.3.4.dist-info/WHEEL
gptfy-0.3.4.dist-info/top_level.txt
gptfy-0.3.4.dist-info/RECORD
