Metadata-Version: 2.1
Name: gptfy
Version: 0.3.4
Summary: UNKNOWN
Home-page: UNKNOWN
License: UNKNOWN
Platform: UNKNOWN
License-File: LICENSE
Requires-Dist: openai ~=0.28.1
